<?xml version="1.0" encoding="UTF-8"?>
<recipe>
    <name>Sate Daging (Indonesian Sate's)</name>
    <indexCharacter>S</indexCharacter>
    <notes></notes>
    <servings>0</servings>
    <instructions>Dice the meat in to 3/4 in. square cubes and put onto bamboo skewers that have been soaked in water (about 4 per stick).

Combine all the marinade ingredients, except the lemon grass, into a food processor and make into a smooth paste. Poor this over the prepared sate's, add the lemon grass, and leave to marinade for at least 2 hours.

Cook the sate's on the barbecue or under the grill for 5 -10 min. until done and serve with Sate dip or hot Peanut Sauce.</instructions>
    <ingredients>
        <ingredient>
            <quantity>1-1/10</quantity>
            <unitOfMeasure>lb</unitOfMeasure>
            <ingredientName>Beef, Pork or Chicken</ingredientName>
            <processingInstructions></processingInstructions>
        </ingredient>
        <ingredient>
            <quantity>1</quantity>
            <unitOfMeasure>ea</unitOfMeasure>
            <ingredientName>Onion</ingredientName>
            <processingInstructions></processingInstructions>
        </ingredient>
        <ingredient>
            <quantity>1</quantity>
            <unitOfMeasure>ea</unitOfMeasure>
            <ingredientName>Garlic clove</ingredientName>
            <processingInstructions></processingInstructions>
        </ingredient>
        <ingredient>
            <quantity>2</quantity>
            <unitOfMeasure>tbsp</unitOfMeasure>
            <ingredientName>Kecap Manis (See Recipe Below)</ingredientName>
            <processingInstructions></processingInstructions>
        </ingredient>
        <ingredient>
            <quantity>1</quantity>
            <unitOfMeasure>tsp</unitOfMeasure>
            <ingredientName>Coriander powder</ingredientName>
            <processingInstructions></processingInstructions>
        </ingredient>
        <ingredient>
            <quantity>1</quantity>
            <unitOfMeasure>tsp</unitOfMeasure>
            <ingredientName>Cummin powder</ingredientName>
            <processingInstructions></processingInstructions>
        </ingredient>
        <ingredient>
            <quantity>1</quantity>
            <unitOfMeasure>ea</unitOfMeasure>
            <ingredientName>stalk Lemon Grass (crushed)</ingredientName>
            <processingInstructions></processingInstructions>
        </ingredient>
        <ingredient>
            <quantity>1</quantity>
            <unitOfMeasure>tsp</unitOfMeasure>
            <ingredientName>Sambal Ulek (Chili Vinegar Paste)</ingredientName>
            <processingInstructions></processingInstructions>
        </ingredient>
        <ingredient>
            <quantity>2</quantity>
            <unitOfMeasure>tbsp</unitOfMeasure>
            <ingredientName>water</ingredientName>
            <processingInstructions></processingInstructions>
        </ingredient>
    </ingredients>
</recipe>
