<?xml version="1.0" encoding="UTF-8"?>
<recipe>
    <name>Spiced Cider</name>
    <indexCharacter>S</indexCharacter>
    <notes></notes>
    <servings>10</servings>
    <instructions>Bring water, spices and sugar to a boil. Add juices and cider. Simmer for at least 30 minutes. Serve warm.</instructions>
    <ingredients>
        <ingredient>
            <quantity>4</quantity>
            <unitOfMeasure>c</unitOfMeasure>
            <ingredientName>Water</ingredientName>
            <processingInstructions></processingInstructions>
        </ingredient>
        <ingredient>
            <quantity>1-1/2</quantity>
            <unitOfMeasure>t</unitOfMeasure>
            <ingredientName>Ginger, Ground</ingredientName>
            <processingInstructions></processingInstructions>
        </ingredient>
        <ingredient>
            <quantity>1</quantity>
            <unitOfMeasure>ea</unitOfMeasure>
            <ingredientName>Cinnamon Stick</ingredientName>
            <processingInstructions></processingInstructions>
        </ingredient>
        <ingredient>
            <quantity>1-1/2</quantity>
            <unitOfMeasure>t</unitOfMeasure>
            <ingredientName>Cloves, Ground</ingredientName>
            <processingInstructions></processingInstructions>
        </ingredient>
        <ingredient>
            <quantity>1</quantity>
            <unitOfMeasure>c</unitOfMeasure>
            <ingredientName>Sugar</ingredientName>
            <processingInstructions></processingInstructions>
        </ingredient>
        <ingredient>
            <quantity>2</quantity>
            <unitOfMeasure>ea</unitOfMeasure>
            <ingredientName>Lemons, Juiced</ingredientName>
            <processingInstructions></processingInstructions>
        </ingredient>
        <ingredient>
            <quantity>2</quantity>
            <unitOfMeasure>ea</unitOfMeasure>
            <ingredientName>Oranges, Juiced</ingredientName>
            <processingInstructions></processingInstructions>
        </ingredient>
        <ingredient>
            <quantity>1/2</quantity>
            <unitOfMeasure>ea</unitOfMeasure>
            <ingredientName>Gallon Apple Cider</ingredientName>
            <processingInstructions></processingInstructions>
        </ingredient>
    </ingredients>
</recipe>
