<?xml version="1.0" encoding="UTF-8"?>
<recipe>
    <name>Tandoori Murghi</name>
    <indexCharacter>T</indexCharacter>
    <notes></notes>
    <servings>0</servings>
    <instructions>Make 3-4 cuts in each chicken quarter using a knife.  Put the chicken in an ovenproof dish. Rub lemon juice into the incisions. Cover it. Let it marinate for about 30 minutes. 

Combine garlic, ginger and green chilli and water in a blender. Grind to make a smooth paste like mixture. Combine the paste with the yogurt, ground cumin, garam masala, paprika, salt, food coloring and melted ghee. Mix all the ingredients well. Spread them over marinated chicken pieces. Coat the pieces with the yogurt marinade. Cover it. Let it marinate at room temperature for about 5 hours. Turn once or twice at the most. 

Place chicken in the oven at 325 F. Let it roast for 1 hour. Baste frequently and turn once. The chicken should be tender and most of the marinade should be evaporated. 

Then grill the chicken over hot charcoal. 

Garnish it with lemon wedges and onion rings.</instructions>
    <ingredients>
        <ingredient>
            <quantity>4</quantity>
            <unitOfMeasure>ea</unitOfMeasure>
            <ingredientName>skinned Chicken Quarters</ingredientName>
            <processingInstructions></processingInstructions>
        </ingredient>
        <ingredient>
            <quantity>2</quantity>
            <unitOfMeasure>tbsp</unitOfMeasure>
            <ingredientName>Lemon Juice (Nimbu Ka Raas)</ingredientName>
            <processingInstructions></processingInstructions>
        </ingredient>
        <ingredient>
            <quantity>1</quantity>
            <unitOfMeasure>ea</unitOfMeasure>
            <ingredientName>Garlic Clove (Lasun)</ingredientName>
            <processingInstructions></processingInstructions>
        </ingredient>
        <ingredient>
            <quantity>1</quantity>
            <unitOfMeasure>in</unitOfMeasure>
            <ingredientName>piece fresh ginger (Adrak), peeled and coarsely chopped</ingredientName>
            <processingInstructions></processingInstructions>
        </ingredient>
        <ingredient>
            <quantity>1</quantity>
            <unitOfMeasure>ea</unitOfMeasure>
            <ingredientName>Green chilli (Hari mirch)</ingredientName>
            <processingInstructions></processingInstructions>
        </ingredient>
        <ingredient>
            <quantity>1</quantity>
            <unitOfMeasure>tbsp</unitOfMeasure>
            <ingredientName>Water</ingredientName>
            <processingInstructions></processingInstructions>
        </ingredient>
        <ingredient>
            <quantity>4</quantity>
            <unitOfMeasure>tbsp</unitOfMeasure>
            <ingredientName>Natural Yogurt (Dahi)</ingredientName>
            <processingInstructions></processingInstructions>
        </ingredient>
        <ingredient>
            <quantity>1</quantity>
            <unitOfMeasure>tsp</unitOfMeasure>
            <ingredientName>Ground Cumin (Jeera)</ingredientName>
            <processingInstructions></processingInstructions>
        </ingredient>
        <ingredient>
            <quantity>1</quantity>
            <unitOfMeasure>tsp</unitOfMeasure>
            <ingredientName>Garam masala</ingredientName>
            <processingInstructions></processingInstructions>
        </ingredient>
        <ingredient>
            <quantity>1</quantity>
            <unitOfMeasure>tsp</unitOfMeasure>
            <ingredientName>Paprika</ingredientName>
            <processingInstructions></processingInstructions>
        </ingredient>
        <ingredient>
            <quantity>1</quantity>
            <unitOfMeasure>tsp</unitOfMeasure>
            <ingredientName>Salt (Namak)</ingredientName>
            <processingInstructions></processingInstructions>
        </ingredient>
        <ingredient>
            <quantity>0</quantity>
            <unitOfMeasure>-</unitOfMeasure>
            <ingredientName>A few drop of Yellow Food Coloring</ingredientName>
            <processingInstructions></processingInstructions>
        </ingredient>
        <ingredient>
            <quantity>2</quantity>
            <unitOfMeasure>tbsp</unitOfMeasure>
            <ingredientName>melted clarified butter (Ghee)</ingredientName>
            <processingInstructions></processingInstructions>
        </ingredient>
        <ingredient>
            <quantity>0</quantity>
            <unitOfMeasure>-</unitOfMeasure>
            <ingredientName>For garnishing:</ingredientName>
            <processingInstructions></processingInstructions>
        </ingredient>
        <ingredient>
            <quantity>0</quantity>
            <unitOfMeasure>-</unitOfMeasure>
            <ingredientName>Lemon Wedges</ingredientName>
            <processingInstructions></processingInstructions>
        </ingredient>
        <ingredient>
            <quantity>0</quantity>
            <unitOfMeasure>-</unitOfMeasure>
            <ingredientName>Onion (Pyaj) rings</ingredientName>
            <processingInstructions></processingInstructions>
        </ingredient>
    </ingredients>
</recipe>
