<?xml version="1.0" encoding="UTF-8"?>
<recipe>
    <name>Rib Dry Rub</name>
    <indexCharacter>R</indexCharacter>
    <notes></notes>
    <servings>4</servings>
    <instructions>Combine all ingredients in a large bowl and mix well. Store in an airtight container. Pack on the dry rub onto your next rack of ribs.</instructions>
    <ingredients>
        <ingredient>
            <quantity>1</quantity>
            <unitOfMeasure>T</unitOfMeasure>
            <ingredientName>Cumin</ingredientName>
            <processingInstructions></processingInstructions>
        </ingredient>
        <ingredient>
            <quantity>1</quantity>
            <unitOfMeasure>T</unitOfMeasure>
            <ingredientName>Paprika</ingredientName>
            <processingInstructions></processingInstructions>
        </ingredient>
        <ingredient>
            <quantity>1</quantity>
            <unitOfMeasure>T</unitOfMeasure>
            <ingredientName>Granulated Garlic</ingredientName>
            <processingInstructions></processingInstructions>
        </ingredient>
        <ingredient>
            <quantity>1</quantity>
            <unitOfMeasure>T</unitOfMeasure>
            <ingredientName>Granulated Onion</ingredientName>
            <processingInstructions></processingInstructions>
        </ingredient>
        <ingredient>
            <quantity>1</quantity>
            <unitOfMeasure>T</unitOfMeasure>
            <ingredientName>Chili Powder</ingredientName>
            <processingInstructions></processingInstructions>
        </ingredient>
        <ingredient>
            <quantity>1</quantity>
            <unitOfMeasure>T</unitOfMeasure>
            <ingredientName>Brown Sugar</ingredientName>
            <processingInstructions></processingInstructions>
        </ingredient>
        <ingredient>
            <quantity>2</quantity>
            <unitOfMeasure>T</unitOfMeasure>
            <ingredientName>Kosher Salt</ingredientName>
            <processingInstructions></processingInstructions>
        </ingredient>
        <ingredient>
            <quantity>1</quantity>
            <unitOfMeasure>t</unitOfMeasure>
            <ingredientName>Cayenne Pepper</ingredientName>
            <processingInstructions></processingInstructions>
        </ingredient>
        <ingredient>
            <quantity>1</quantity>
            <unitOfMeasure>t</unitOfMeasure>
            <ingredientName>Black Pepper</ingredientName>
            <processingInstructions></processingInstructions>
        </ingredient>
        <ingredient>
            <quantity>1</quantity>
            <unitOfMeasure>t</unitOfMeasure>
            <ingredientName>White Pepper</ingredientName>
            <processingInstructions></processingInstructions>
        </ingredient>
    </ingredients>
</recipe>
